holidays_jp/__init__.py
holidays_jp/tests.py
holidays_jp/countries/__init__.py
holidays_jp/countries/jp.py
holidays_jp/countries/us.py
holidays_jp-1.0.2.dist-info/METADATA
holidays_jp-1.0.2.dist-info/RECORD
holidays_jp-1.0.2.dist-info/WHEEL
holidays_jp-1.0.2.dist-info/top_level.txt
holidays_jp-1.0.2.dist-info/zip-safe
