Metadata-Version: 2.1
Name: holidays-jp
Version: 1.0.2
Summary: Calculate the Japanese holidays since 1948.
Home-page: https://github.com/mokejp/holidays_jp
Author: mo.kejp
Author-email: UNKNOWN
License: MIT License
Keywords: holidays_jp,holidays-jp,holiday,japanese,japan
Platform: UNKNOWN
Classifier: License :: OSI Approved :: MIT License
Classifier: Programming Language :: Python
Classifier: Programming Language :: Python :: 2.7
Requires-Dist: python-dateutil
